xspec_models_cxc_helpers/__init__.py
xspec_models_cxc_helpers/data/xspec.h
xspec_models_cxc_helpers/data/xsudmget.cxx
xspec_models_cxc_helpers/data/xsudmget64.cxx
xspec_models_cxc_helpers/tests/test_utils.py
xspec_models_cxc_helpers-0.1.0.dist-info/LICENSE
xspec_models_cxc_helpers-0.1.0.dist-info/METADATA
xspec_models_cxc_helpers-0.1.0.dist-info/WHEEL
xspec_models_cxc_helpers-0.1.0.dist-info/top_level.txt
xspec_models_cxc_helpers-0.1.0.dist-info/RECORD
