Metadata-Version: 2.1
Name: xspec_models_cxc_helpers
Version: 0.1.0
Summary: Helper routines for xspec-models-cxc **experimental**
Author-email: Douglas Burke <dburke@cfa.harvard.edu>
License: GNU GENERAL PUBLIC LICENSE
Project-URL: Repository, https://github.com/cxcsds/xspec-models-cxc-helpers
Project-URL: Issues, https://github.com/cxcsds/xspec-models-cxc-helpers/issues
Classifier: Development Status :: 3 - Alpha
Classifier: Intended Audience :: Science/Research
Classifier: License :: OSI Approved :: GNU General Public License v3 or later (GPLv3+)
Classifier: Programming Language :: Python :: 3.10
Classifier: Programming Language :: Python :: 3.11
Classifier: Programming Language :: Python :: 3.12
Classifier: Topic :: Scientific/Engineering :: Astronomy
Classifier: Topic :: Scientific/Engineering :: Physics
Requires-Python: >=3.10
License-File: LICENSE
Provides-Extra: test
Requires-Dist: pytest ; extra == 'test'
Requires-Dist: parse-xspec ; extra == 'test'
